async_stripe/__init__.py
async_stripe/api_requestor.py
async_stripe/api_resources/__init__.py
async_stripe/api_resources/abstract/__init__.py
async_stripe/api_resources/abstract/api_resource.py
async_stripe/api_resources/abstract/custom_method.py
async_stripe/api_resources/abstract/listable_api_resource.py
async_stripe/api_resources/abstract/nested_resource_class_methods.py
async_stripe/api_resources/abstract/test_helpers.py
async_stripe/api_resources/abstract/updateable_api_resource.py
async_stripe/api_resources/account.py
async_stripe/api_resources/application_fee.py
async_stripe/api_resources/application_fee_refund.py
async_stripe/api_resources/bank_account.py
async_stripe/api_resources/capability.py
async_stripe/api_resources/card.py
async_stripe/api_resources/charge.py
async_stripe/api_resources/customer.py
async_stripe/api_resources/ephermal_key.py
async_stripe/api_resources/file.py
async_stripe/api_resources/list_object.py
async_stripe/api_resources/person.py
async_stripe/api_resources/quote.py
async_stripe/api_resources/reversal.py
async_stripe/api_resources/search_result_object.py
async_stripe/api_resources/source.py
async_stripe/api_resources/transfer.py
async_stripe/api_resources/usage_record.py
async_stripe/http_client.py
async_stripe/oauth.py
async_stripe/stripe_object.py
async_stripe-6.0.0.dist-info/LICENSE.stripe.txt
async_stripe-6.0.0.dist-info/LICENSE.txt
async_stripe-6.0.0.dist-info/METADATA
async_stripe-6.0.0.dist-info/WHEEL
async_stripe-6.0.0.dist-info/RECORD
