Metadata-Version: 2.1
Name: async-stripe
Version: 6.0.0
Summary: An asynchronous wrapper around Stripe's official python library.
Home-page: https://github.com/bhch/async-stripe
License: BSD 3-Clause
Keywords: stripe,async,asynchronous,wrapper
Author: Bharat Chauhan
Author-email: tell.bhch@gmail.com
Maintainer: Bharat Chauhan
Maintainer-email: tell.bhch@gmail.com
Requires-Python: >=3.6,<4.0
Classifier: License :: Other/Proprietary License
Classifier: Programming Language :: Python :: 3
Classifier: Programming Language :: Python :: 3.6
Classifier: Programming Language :: Python :: 3.7
Classifier: Programming Language :: Python :: 3.8
Classifier: Programming Language :: Python :: 3.9
Classifier: Programming Language :: Python :: 3.10
Classifier: Programming Language :: Python :: 3.11
Requires-Dist: stripe (==6.0.0)
Requires-Dist: tornado (>=5.1)
Project-URL: Repository, https://github.com/bhch/async-stripe
